hdc_rs_py/__init__.py
hdc_rs_py/hdc_rs_py.cpython-310-i386-linux-gnu.so
hdc_rs_py-0.1.2.dist-info/METADATA
hdc_rs_py-0.1.2.dist-info/WHEEL
hdc_rs_py-0.1.2.dist-info/RECORD
