Metadata-Version: 2.4
Name: hdc-rs-py
Version: 0.1.2
Classifier: Programming Language :: Rust
Classifier: Programming Language :: Python :: Implementation :: CPython
Classifier: Programming Language :: Python :: Implementation :: PyPy
Classifier: Programming Language :: Python :: 3
Classifier: Programming Language :: Python :: 3.8
Classifier: Programming Language :: Python :: 3.9
Classifier: Programming Language :: Python :: 3.10
Classifier: Programming Language :: Python :: 3.11
Classifier: Programming Language :: Python :: 3.12
Classifier: License :: OSI Approved :: MIT License
Classifier: License :: OSI Approved :: Apache Software License
Summary: Python bindings for HarmonyOS Device Connector (HDC) client library
Keywords: harmonyos,hdc,device,connector,openharmony
Home-Page: https://github.com/oslo254804746/hdc-rs
Author: HDC-RS Contributors
Requires-Python: >=3.8
